{
  "main": {
    "name": "Shikhar Srivastava",
    "occupation": "FRONT END DEVELOPER",
    "description": "I like to design beatiful things",
    "image": "profile-shikhar.jpg",
    "bio": "Hi there! I am Sangam! You might also call me Sangam. With a passion for learning new technologies and ability to solve problems in a smart way, I have the mindset to work with full dedication and give my best in whatever I do. I aspire to dive deep into the technological world. As an upbeat, self-motivated team player with excellent communication, I envision an exciting future in the industry. Browse my site to see all that I have to offer. With a passion for learning new technologies and ability to solve problems in a smart way, I have the mindset to work with full dedication and give my best in whatever I do.I have the mindset to work with full dedication and give my best in whatever I do. ",
    "contactmessage": "Got an idea to work on, get in touch with me, I usually reply within 24 hours!",
    "email": "shikhar.17.srivastava@st.niituniversity.in",
    "phone": "+91 930 4298 936",
    "address": {
      "street": "H. No. 129",
      "city": "Hazaribagh",
      "state": "Jharkhand",
      "country": "India",
      "zip": "825301"
    },
    "website": "https://shikhar17srivastav.wixsite.com/portfolio",
    "resumedownload": "https://shikhar17srivastav.wixsite.com/portfolio",
    "social": [
      {
        "name": "youtube",
        "url": "https://www.facebook.com/profile.php?id=100006803926273",
        "className": "fa fa-youtube"
      },
      {
        "name": "facebook",
        "url": "https://www.facebook.com/profile.php?id=100006803926273",
        "className": "fa fa-facebook"
      },
      {
        "name": "linkedin",
        "url": "https://www.linkedin.com/in/shikhar-srivastava-9b219219a/",
        "className": "fa fa-linkedin"
      },
      {
        "name": "instagram",
        "url": "https://www.instagram.com/sangamshikhar/",
        "className": "fa fa-instagram"
      },
      {
        "name": "github",
        "url": "https://github.com/shikhar1020",
        "className": "fa fa-github"
      }
    ]
  },
  "resume": {
    "skillmessage": "View my Technical Skills Proficiency",
    "education": [
      {
        "school": "NIIT University",
        "degree": "B. Tech.  Computer Science",
        "graduated": "July 2021",
        "description": "• Got a scholarship of 75% on the total of academic fees for two consecutive years."
      }
    ],
    "work": [
      {
        "company": "Eoraa Consultancy",
        "title": "Front End Developer",
        "years": "November 2020 - Present",
        "description": "Developed a platform for medical proffesionals across japan to connect and collaborate with each other. Along with, advertiser management platform to serve ads to users and a CMS (Content Management System) to view and modify the data."
      }
    ],
    "skills": [
      {
        "name": "ReactJs",
        "level": "75%"
      },
      {
        "name": "Javascript",
        "level": "60%"
      },
      {
        "name": "HTML5",
        "level": "87%"
      },
      {
        "name": "CSS3",
        "level": "80%"
      },
      {
        "name": "GraphQl",
        "level": "70%"
      },
      {
        "name": "Firebase",
        "level": "70%"
      },
      {
        "name": "Git & Github",
        "level": "95%"
      },
      {
        "name": "Redux",
        "level": "60%"
      },
      {
        "name": "Python",
        "level": "67%"
      },
      {
        "name": "C++",
        "level": "60%"
      }
    ]
  },
  "portfolio": {
    "projects": [
      {
        "title": "Instagram Clone",
        "category": "",
        "image": "instagram.PNG",
        "url": "https://instagram-clone-76c99.web.app/"
      },
      {
        "title": "Amazon Clone",
        "category": "",
        "image": "amazon.PNG",
        "url": "https://clone-4277b.web.app/"
      },
      {
        "title": "Youtube Clone",
        "category": "",
        "image": "youtube.PNG",
        "url": "https://clone-c7710.web.app/"
      },
      {
        "title": "WhatsApp Clone",
        "category": "",
        "image": "whatsapp.PNG",
        "url": "https://whatsappclonemern-7b264.web.app/"
      },
      {
        "title": "Photo Polish",
        "category": "",
        "image": "photoPolish.PNG",
        "url": "https://shikhar1020.github.io/photo-polish/"
      },
      {
        "title": "Photo Polish",
        "category": "",
        "image": "whatsappLogo.png",
        "url": "https://shikhar1020.github.io/photo-polish/"
      },
      {
        "title": "Photo Polish",
        "category": "",
        "image": "whatsappLogo.png",
        "url": "https://shikhar1020.github.io/photo-polish/"
      },
      {
        "title": "Photo Polish",
        "category": "",
        "image": "whatsappLogo.png",
        "url": "https://shikhar1020.github.io/photo-polish/"
      },
      {
        "title": "Photo Polish",
        "category": "",
        "image": "whatsappLogo.png",
        "url": "https://shikhar1020.github.io/photo-polish/"
      },
      {
        "title": "Netflix Clone",
        "category": "",
        "image": "netflix.PNG",
        "url": "https://netflix-clone-500d3.web.app/"
      }
    ]
  },
  "testimonials": {
    "testimonials": [
      {
        "text": "Shikhar is absolutely excellent, his depth of knowledge & his mentorship really meant a lot to us... I would definitely recommend",
        "user": "Jorge Fouto",
        "userDesignation": "CEO at Eoraa Contulsancy"
      },
      {
        "text": "Learning with Shikhar has been AWESOME, he makes learning React so easy and approachable, you'll finally feel like you know what's going on!",
        "user": "Varun Modgil",
        "userDesignation": "CEO at Eoraa Contulsancy"
      }
    ]
  }
}